Workbook

Sheet Summary
A1: Cash In / Cash Out Summary
A2: Every figure below is a formula. Change the Transactions sheet and this updates.
A4: Measure | B4: Value | C4: Note
A5: Cash in | B5: =SUM(Transactions!F5:F43) | C5: Total receipts
A6: Cash out | B6: =SUM(Transactions!G5:G43) | C6: Total payments
A7: Net result | B7: =SUM(Transactions!H5:H43) | C7: Cash basis, not statutory profit
A8: Cost ratio | B8: =SUM(Transactions!G5:G43)/SUM(Transactions!F5:F43) | C8: Spent per £1 received
A9: Transactions | B9: =COUNT(Transactions!H5:H43) | C9: Lines in the statement
A10: Months covered | B10: =COUNT('Monthly cash flow'!D5:D16) | C10: Periods in the data
A11: Missing documents | B11: =COUNTBLANK(Transactions!E5:E43) | C11: Should be zero
A12: Best month | B12: =MAX('Monthly cash flow'!D5:D16) | C12: Largest net inflow
A13: Worst month | B13: =MIN('Monthly cash flow'!D5:D16) | C13: Largest net outflow
A16: How to read this workbook
A17: Transactions - the cleaned bank statement. Columns H to K are calculated; the rest is source data.
A18: Categories - the keyword rules. Blue text on yellow means you may edit it; everything else is a formula.
A19: Monthly cash flow - SUMIFS by month, with a running total.
A20: Profit and loss - SUMIFS by category, income then expenditure.
A21: By company - what has accumulated with each counterparty.
A23: Basis: cash accounting. Receipts and payments as they cleared the bank. No accruals, prepayments, depreciation or tax.

Sheet Transactions
A1: Transactions
A2: One row per bank line. Columns H to K are calculated - do not type over them.
A4: Date | B4: Description | C4: Counterparty | D4: Property | E4: Document | F4: Money in | G4: Money out | H4: Amount | I4: Direction | J4: Category | K4: Month
A5: 45748 | B5: COMMERCIAL RENT COMM-04 | C5: TENANT - KESTREL TRADING LTD | D5: COMM-04 | E5: RENT-COMM-04-202504 | F5: 3200 | G5: 0 | H5: =F5-G5 | I5: =IF(H5>=0,"Cash in","Cash out") | J5: =IFERROR(INDEX(Categories!$B$5:$B$19,MATCH(1,INDEX(--ISNUMBER(SEARCH(Categories!$A$5:$A$19,UPPER($B5))),0),0)),IF(H5>=0,"Uncategorised income","Uncategorised expense")) | K5: =TEXT(A5,"yyyy-mm")
A6: 45750 | B6: COMMERCIAL MORTGAGE INTEREST COMM-04 | C6: MERIDIAN COMMERCIAL | D6: COMM-04 | E6: CMTG-202504 | F6: 0 | G6: 1450 | H6: =F6-G6 | I6: =IF(H6>=0,"Cash in","Cash out") | J6: =IFERROR(INDEX(Categories!$B$5:$B$19,MATCH(1,INDEX(--ISNUMBER(SEARCH(Categories!$A$5:$A$19,UPPER($B6))),0),0)),IF(H6>=0,"Uncategorised income","Uncategorised expense")) | K6: =TEXT(A6,"yyyy-mm")
A7: 45752 | B7: MANAGING AGENT COMM-04 | C7: HORIZON COMMERCIAL | D7: COMM-04 | E7: INV-HC-202504 | F7: 0 | G7: 256 | H7: =F7-G7 | I7: =IF(H7>=0,"Cash in","Cash out") | J7: =IFERROR(INDEX(Categories!$B$5:$B$19,MATCH(1,INDEX(--ISNUMBER(SEARCH(Categories!$A$5:$A$19,UPPER($B7))),0),0)),IF(H7>=0,"Uncategorised income","Uncategorised expense")) | K7: =TEXT(A7,"yyyy-mm")
A8: 45778 | B8: COMMERCIAL RENT COMM-04 | C8: TENANT - KESTREL TRADING LTD | D8: COMM-04 | E8: RENT-COMM-04-202505 | F8: 3200 | G8: 0 | H8: =F8-G8 | I8: =IF(H8>=0,"Cash in","Cash out") | J8: =IFERROR(INDEX(Categories!$B$5:$B$19,MATCH(1,INDEX(--ISNUMBER(SEARCH(Categories!$A$5:$A$19,UPPER($B8))),0),0)),IF(H8>=0,"Uncategorised income","Uncategorised expense")) | K8: =TEXT(A8,"yyyy-mm")
A9: 45780 | B9: COMMERCIAL MORTGAGE INTEREST COMM-04 | C9: MERIDIAN COMMERCIAL | D9: COMM-04 | E9: CMTG-202505 | F9: 0 | G9: 1450 | H9: =F9-G9 | I9: =IF(H9>=0,"Cash in","Cash out") | J9: =IFERROR(INDEX(Categories!$B$5:$B$19,MATCH(1,INDEX(--ISNUMBER(SEARCH(Categories!$A$5:$A$19,UPPER($B9))),0),0)),IF(H9>=0,"Uncategorised income","Uncategorised expense")) | K9: =TEXT(A9,"yyyy-mm")
A10: 45782 | B10: MANAGING AGENT COMM-04 | C10: HORIZON COMMERCIAL | D10: COMM-04 | E10: INV-HC-202505 | F10: 0 | G10: 256 | H10: =F10-G10 | I10: =IF(H10>=0,"Cash in","Cash out") | J10: =IFERROR(INDEX(Categories!$B$5:$B$19,MATCH(1,INDEX(--ISNUMBER(SEARCH(Categories!$A$5:$A$19,UPPER($B10))),0),0)),IF(H10>=0,"Uncategorised income","Uncategorised expense")) | K10: =TEXT(A10,"yyyy-mm")
A11: 45809 | B11: COMMERCIAL RENT COMM-04 | C11: TENANT - KESTREL TRADING LTD | D11: COMM-04 | E11: RENT-COMM-04-202506 | F11: 3200 | G11: 0 | H11: =F11-G11 | I11: =IF(H11>=0,"Cash in","Cash out") | J11: =IFERROR(INDEX(Categories!$B$5:$B$19,MATCH(1,INDEX(--ISNUMBER(SEARCH(Categories!$A$5:$A$19,UPPER($B11))),0),0)),IF(H11>=0,"Uncategorised income","Uncategorised expense")) | K11: =TEXT(A11,"yyyy-mm")
A12: 45811 | B12: COMMERCIAL MORTGAGE INTEREST COMM-04 | C12: MERIDIAN COMMERCIAL | D12: COMM-04 | E12: CMTG-202506 | F12: 0 | G12: 1450 | H12: =F12-G12 | I12: =IF(H12>=0,"Cash in","Cash out") | J12: =IFERROR(INDEX(Categories!$B$5:$B$19,MATCH(1,INDEX(--ISNUMBER(SEARCH(Categories!$A$5:$A$19,UPPER($B12))),0),0)),IF(H12>=0,"Uncategorised income","Uncategorised expense")) | K12: =TEXT(A12,"yyyy-mm")
A13: 45813 | B13: MANAGING AGENT COMM-04 | C13: HORIZON COMMERCIAL | D13: COMM-04 | E13: INV-HC-202506 | F13: 0 | G13: 256 | H13: =F13-G13 | I13: =IF(H13>=0,"Cash in","Cash out") | J13: =IFERROR(INDEX(Categories!$B$5:$B$19,MATCH(1,INDEX(--ISNUMBER(SEARCH(Categories!$A$5:$A$19,UPPER($B13))),0),0)),IF(H13>=0,"Uncategorised income","Uncategorised expense")) | K13: =TEXT(A13,"yyyy-mm")
A14: 45838 | B14: DIRECTORS REMUNERATION | C14: R MEHRA | D14: Company-wide | E14: PAYROLL-2025-06 | F14: 0 | G14: 9100 | H14: =F14-G14 | I14: =IF(H14>=0,"Cash in","Cash out") | J14: =IFERROR(INDEX(Categories!$B$5:$B$19,MATCH(1,INDEX(--ISNUMBER(SEARCH(Categories!$A$5:$A$19,UPPER($B14))),0),0)),IF(H14>=0,"Uncategorised income","Uncategorised expense")) | K14: =TEXT(A14,"yyyy-mm")
A15: 45839 | B15: COMMERCIAL RENT COMM-04 | C15: TENANT - KESTREL TRADING LTD | D15: COMM-04 | E15: RENT-COMM-04-202507 | F15: 3200 | G15: 0 | H15: =F15-G15 | I15: =IF(H15>=0,"Cash in","Cash out") | J15: =IFERROR(INDEX(Categories!$B$5:$B$19,MATCH(1,INDEX(--ISNUMBER(SEARCH(Categories!$A$5:$A$19,UPPER($B15))),0),0)),IF(H15>=0,"Uncategorised income","Uncategorised expense")) | K15: =TEXT(A15,"yyyy-mm")
A16: 45841 | B16: COMMERCIAL MORTGAGE INTEREST COMM-04 | C16: MERIDIAN COMMERCIAL | D16: COMM-04 | E16: CMTG-202507 | F16: 0 | G16: 1450 | H16: =F16-G16 | I16: =IF(H16>=0,"Cash in","Cash out") | J16: =IFERROR(INDEX(Categories!$B$5:$B$19,MATCH(1,INDEX(--ISNUMBER(SEARCH(Categories!$A$5:$A$19,UPPER($B16))),0),0)),IF(H16>=0,"Uncategorised income","Uncategorised expense")) | K16: =TEXT(A16,"yyyy-mm")
... A43: 46086 | B43: MANAGING AGENT COMM-04 | C43: HORIZON COMMERCIAL | D43: COMM-04 | E43: INV-HC-202603 | F43: 0 | G43: 256 | H43: =F43-G43 | I43: =IF(H43>=0,"Cash in","Cash out") | J43: =IFERROR(INDEX(Categories!$B$5:$B$19,MATCH(1,INDEX(--ISNUMBER(SEARCH(Categories!$A$5:$A$19,UPPER($B43))),0),0)),IF(H43>=0,"Uncategorised income","Uncategorised expense")) | K43: =TEXT(A43,"yyyy-mm")
E44: Total | F44: =SUM(F5:F43) | G44: =SUM(G5:G43) | H44: =SUM(H5:H43)

Sheet Monthly cash flow
A1: Monthly cash flow
A2: Totalled straight from the Transactions sheet with SUMIFS.
A4: Month | B4: Cash in | C4: Cash out | D4: Net movement | E4: Running total
A5: 2025-04 | B5: =SUMIFS(Transactions!$F$5:$F$43,Transactions!$K$5:$K$43,$A5) | C5: =SUMIFS(Transactions!$G$5:$G$43,Transactions!$K$5:$K$43,$A5) | D5: =B5-C5 | E5: =D5
A6: 2025-05 | B6: =SUMIFS(Transactions!$F$5:$F$43,Transactions!$K$5:$K$43,$A6) | C6: =SUMIFS(Transactions!$G$5:$G$43,Transactions!$K$5:$K$43,$A6) | D6: =B6-C6 | E6: =E5+D6
A7: 2025-06 | B7: =SUMIFS(Transactions!$F$5:$F$43,Transactions!$K$5:$K$43,$A7) | C7: =SUMIFS(Transactions!$G$5:$G$43,Transactions!$K$5:$K$43,$A7) | D7: =B7-C7 | E7: =E6+D7
A8: 2025-07 | B8: =SUMIFS(Transactions!$F$5:$F$43,Transactions!$K$5:$K$43,$A8) | C8: =SUMIFS(Transactions!$G$5:$G$43,Transactions!$K$5:$K$43,$A8) | D8: =B8-C8 | E8: =E7+D8
A9: 2025-08 | B9: =SUMIFS(Transactions!$F$5:$F$43,Transactions!$K$5:$K$43,$A9) | C9: =SUMIFS(Transactions!$G$5:$G$43,Transactions!$K$5:$K$43,$A9) | D9: =B9-C9 | E9: =E8+D9
A10: 2025-09 | B10: =SUMIFS(Transactions!$F$5:$F$43,Transactions!$K$5:$K$43,$A10) | C10: =SUMIFS(Transactions!$G$5:$G$43,Transactions!$K$5:$K$43,$A10) | D10: =B10-C10 | E10: =E9+D10
A11: 2025-10 | B11: =SUMIFS(Transactions!$F$5:$F$43,Transactions!$K$5:$K$43,$A11) | C11: =SUMIFS(Transactions!$G$5:$G$43,Transactions!$K$5:$K$43,$A11) | D11: =B11-C11 | E11: =E10+D11
A12: 2025-11 | B12: =SUMIFS(Transactions!$F$5:$F$43,Transactions!$K$5:$K$43,$A12) | C12: =SUMIFS(Transactions!$G$5:$G$43,Transactions!$K$5:$K$43,$A12) | D12: =B12-C12 | E12: =E11+D12
A13: 2025-12 | B13: =SUMIFS(Transactions!$F$5:$F$43,Transactions!$K$5:$K$43,$A13) | C13: =SUMIFS(Transactions!$G$5:$G$43,Transactions!$K$5:$K$43,$A13) | D13: =B13-C13 | E13: =E12+D13
A14: 2026-01 | B14: =SUMIFS(Transactions!$F$5:$F$43,Transactions!$K$5:$K$43,$A14) | C14: =SUMIFS(Transactions!$G$5:$G$43,Transactions!$K$5:$K$43,$A14) | D14: =B14-C14 | E14: =E13+D14
A15: 2026-02 | B15: =SUMIFS(Transactions!$F$5:$F$43,Transactions!$K$5:$K$43,$A15) | C15: =SUMIFS(Transactions!$G$5:$G$43,Transactions!$K$5:$K$43,$A15) | D15: =B15-C15 | E15: =E14+D15
A16: 2026-03 | B16: =SUMIFS(Transactions!$F$5:$F$43,Transactions!$K$5:$K$43,$A16) | C16: =SUMIFS(Transactions!$G$5:$G$43,Transactions!$K$5:$K$43,$A16) | D16: =B16-C16 | E16: =E15+D16
A17: Total | B17: =SUM(B5:B16) | C17: =SUM(C5:C16) | D17: =SUM(D5:D16)

Sheet Profit and loss
A1: Profit and loss
A2: Cash basis: receipts and payments as they cleared the bank. Not a statutory profit - no accruals, prepayments, depreciation or tax.
B4: Transactions | C4: Amount
A5: INCOME
A6: Rental income | B6: =COUNTIFS(Transactions!$J$5:$J$43,"Rental income") | C6: =SUMIFS(Transactions!$H$5:$H$43,Transactions!$J$5:$J$43,"Rental income")
A7: Total income | C7: =SUM(C6:C6)
A9: EXPENDITURE
A10: Mortgage interest | B10: =COUNTIFS(Transactions!$J$5:$J$43,"Mortgage interest") | C10: =SUMIFS(Transactions!$H$5:$H$43,Transactions!$J$5:$J$43,"Mortgage interest")
A11: Managing agent fees | B11: =COUNTIFS(Transactions!$J$5:$J$43,"Managing agent fees") | C11: =SUMIFS(Transactions!$H$5:$H$43,Transactions!$J$5:$J$43,"Managing agent fees")
A12: Directors remuneration | B12: =COUNTIFS(Transactions!$J$5:$J$43,"Directors remuneration") | C12: =SUMIFS(Transactions!$H$5:$H$43,Transactions!$J$5:$J$43,"Directors remuneration")
A13: Insurance | B13: =COUNTIFS(Transactions!$J$5:$J$43,"Insurance") | C13: =SUMIFS(Transactions!$H$5:$H$43,Transactions!$J$5:$J$43,"Insurance")
A14: Professional fees | B14: =COUNTIFS(Transactions!$J$5:$J$43,"Professional fees") | C14: =SUMIFS(Transactions!$H$5:$H$43,Transactions!$J$5:$J$43,"Professional fees")
A15: Total expenditure | C15: =SUM(C10:C14)
A17: NET RESULT FOR THE PERIOD | C17: =C7+C15
A20: Assumption: every bank line is revenue in nature. No capital items, loan drawdowns or repayments appear in this statement.

Sheet By company
A1: Accumulated by company
A2: Everything paid to or received from each counterparty.
A4: Company | B4: Transactions | C4: Money in | D4: Money out | E4: Accumulated | F4: Share of direction
A5: TENANT - KESTREL TRADING LTD | B5: =COUNTIFS(Transactions!$C$5:$C$43,$A5) | C5: =SUMIFS(Transactions!$F$5:$F$43,Transactions!$C$5:$C$43,$A5) | D5: =SUMIFS(Transactions!$G$5:$G$43,Transactions!$C$5:$C$43,$A5) | E5: =SUMIFS(Transactions!$H$5:$H$43,Transactions!$C$5:$C$43,$A5) | F5: =IF(E5>=0,C5/SUM(Transactions!$F$5:$F$43),D5/SUM(Transactions!$G$5:$G$43))
A6: MERIDIAN COMMERCIAL | B6: =COUNTIFS(Transactions!$C$5:$C$43,$A6) | C6: =SUMIFS(Transactions!$F$5:$F$43,Transactions!$C$5:$C$43,$A6) | D6: =SUMIFS(Transactions!$G$5:$G$43,Transactions!$C$5:$C$43,$A6) | E6: =SUMIFS(Transactions!$H$5:$H$43,Transactions!$C$5:$C$43,$A6) | F6: =IF(E6>=0,C6/SUM(Transactions!$F$5:$F$43),D6/SUM(Transactions!$G$5:$G$43))
A7: R MEHRA | B7: =COUNTIFS(Transactions!$C$5:$C$43,$A7) | C7: =SUMIFS(Transactions!$F$5:$F$43,Transactions!$C$5:$C$43,$A7) | D7: =SUMIFS(Transactions!$G$5:$G$43,Transactions!$C$5:$C$43,$A7) | E7: =SUMIFS(Transactions!$H$5:$H$43,Transactions!$C$5:$C$43,$A7) | F7: =IF(E7>=0,C7/SUM(Transactions!$F$5:$F$43),D7/SUM(Transactions!$G$5:$G$43))
A8: HORIZON COMMERCIAL | B8: =COUNTIFS(Transactions!$C$5:$C$43,$A8) | C8: =SUMIFS(Transactions!$F$5:$F$43,Transactions!$C$5:$C$43,$A8) | D8: =SUMIFS(Transactions!$G$5:$G$43,Transactions!$C$5:$C$43,$A8) | E8: =SUMIFS(Transactions!$H$5:$H$43,Transactions!$C$5:$C$43,$A8) | F8: =IF(E8>=0,C8/SUM(Transactions!$F$5:$F$43),D8/SUM(Transactions!$G$5:$G$43))
A9: WHITFIELD & CO | B9: =COUNTIFS(Transactions!$C$5:$C$43,$A9) | C9: =SUMIFS(Transactions!$F$5:$F$43,Transactions!$C$5:$C$43,$A9) | D9: =SUMIFS(Transactions!$G$5:$G$43,Transactions!$C$5:$C$43,$A9) | E9: =SUMIFS(Transactions!$H$5:$H$43,Transactions!$C$5:$C$43,$A9) | F9: =IF(E9>=0,C9/SUM(Transactions!$F$5:$F$43),D9/SUM(Transactions!$G$5:$G$43))
A10: ALBION INSURANCE | B10: =COUNTIFS(Transactions!$C$5:$C$43,$A10) | C10: =SUMIFS(Transactions!$F$5:$F$43,Transactions!$C$5:$C$43,$A10) | D10: =SUMIFS(Transactions!$G$5:$G$43,Transactions!$C$5:$C$43,$A10) | E10: =SUMIFS(Transactions!$H$5:$H$43,Transactions!$C$5:$C$43,$A10) | F10: =IF(E10>=0,C10/SUM(Transactions!$F$5:$F$43),D10/SUM(Transactions!$G$5:$G$43))
A11: Total | B11: =SUM(B5:B10) | C11: =SUM(C5:C10) | D11: =SUM(D5:D10) | E11: =SUM(E5:E10)

Sheet Categories
A1: Category rules
A2: Edit these to change how transactions are categorised. The first keyword found in the description wins.
A4: Keyword (upper case) | B4: Category | C4: Type
A5: RENT | B5: Rental income | C5: Income
A6: SERVICE CHARGE | B6: Service charge income | C6: Income
A7: MORTGAGE | B7: Mortgage interest | C7: Expense
A8: INTEREST | B8: Mortgage interest | C8: Expense
A9: MANAGING AGENT | B9: Managing agent fees | C9: Expense
A10: AGENT | B10: Managing agent fees | C10: Expense
A11: INSURANCE | B11: Insurance | C11: Expense
A12: ACCOUNTANCY | B12: Professional fees | C12: Expense
A13: LEGAL | B13: Professional fees | C13: Expense
A14: AUDIT | B14: Professional fees | C14: Expense
A15: DIRECTOR | B15: Directors remuneration | C15: Expense
... A19: MAINTENANCE | B19: Repairs and maintenance | C19: Expense
A21: Blue text on yellow = input cells. Everything else in this workbook is calculated.
